{"guid":"root________","title":"","index":0,"dateAdded":1665084254560000,"lastModified":1681933639200000,"id":1,"typeCode":2,"type":"text/x-moz-place-container","root":"placesRoot","children":[{"guid":"menu________","title":"menu","index":0,"dateAdded":1665084254560000,"lastModified":1667094886704000,"id":2,"typeCode":2,"type":"text/x-moz-place-container","root":"bookmarksMenuFolder","children":[{"guid":"CVUxOAGjgHGy","title":"Mozilla Firefox","index":0,"dateAdded":1553034668462000,"lastModified":1676860822000000,"id":7,"typeCode":2,"type":"text/x-moz-place-container"},{"guid":"D4QRtCsFF_Tg","title":"From Google Chrome","index":1,"dateAdded":1553034887201000,"lastModified":1676860822000000,"id":13,"typeCode":2,"type":"text/x-moz-place-container"}]},{"guid":"toolbar_____","title":"toolbar","index":1,"dateAdded":1665084254560000,"lastModified":1675974156035000,"id":3,"typeCode":2,"type":"text/x-moz-place-container","root":"toolbarFolder","children":[{"guid":"xy1D9ivg-LuB","title":"exploit-db","index":0,"dateAdded":1669223385197000,"lastModified":1676860822000000,"id":72,"typeCode":1,"type":"text/x-moz-place","uri":"https://www.exploit-db.com/"},{"guid":"Owsb2zd4Uqh2","title":"CyberChef","index":1,"dateAdded":1669223399036000,"lastModified":1676860822000000,"id":73,"typeCode":1,"iconUri":"https://gchq.github.io/CyberChef/assets/aecc661b69309290f600.ico","type":"text/x-moz-place","uri":"https://gchq.github.io/CyberChef/"},{"guid":"WKXqENoF9U7C","title":"CrackStation - Online Password Hash Cracking - MD5, SHA1, Linux, Rainbow Tables, etc.","index":2,"dateAdded":1669223412370000,"lastModified":1676860822000000,"id":75,"typeCode":1,"type":"text/x-moz-place","uri":"https://crackstation.net/"},{"guid":"UzQKXcMo2KQG","title":"GTFOBins","index":3,"dateAdded":1669223404710000,"lastModified":1676860822000000,"id":74,"typeCode":1,"iconUri":"https://gtfobins.github.io/assets/logo.png","type":"text/x-moz-place","uri":"https://gtfobins.github.io/"}]},{"guid":"unfiled_____","title":"unfiled","index":3,"dateAdded":1665084254560000,"lastModified":1681933639200000,"id":5,"typeCode":2,"type":"text/x-moz-place-container","root":"unfiledBookmarksFolder","children":[{"guid":"TIGW_px5g11P","title":"Free People Search & Reverse Phone Lookup - FastPeopleSearch.com","index":0,"dateAdded":1595109553266000,"lastModified":1676860822000000,"id":25,"typeCode":1,"iconUri":"https://www.fastpeoplesearch.com/apple-touch-icon-180x180.png?v2","type":"text/x-moz-place","uri":"https://www.fastpeoplesearch.com/"},{"guid":"ffphqSuA7M_5","title":"Hacker News","index":1,"dateAdded":1599275341759000,"lastModified":1676860822000000,"id":26,"typeCode":1,"type":"text/x-moz-place","uri":"https://news.ycombinator.com/"},{"guid":"rI8tlmxoTqjh","title":"Introduction · CTF Field Guide","index":2,"dateAdded":1599331620646000,"lastModified":1676860822000000,"id":27,"typeCode":1,"iconUri":"https://trailofbits.github.io/ctf/gitbook/images/apple-touch-icon-precomposed-152.png","type":"text/x-moz-place","uri":"https://trailofbits.github.io/ctf/"},{"guid":"vSvSyQeM_SAa","title":"Epieos Tools","index":3,"dateAdded":1601068979235000,"lastModified":1676860822000000,"id":28,"typeCode":1,"type":"text/x-moz-place","uri":"https://tools.epieos.com/google-account.php"},{"guid":"wOz1C0l4RAUe","title":"ShadyURL - Don't just shorten your URL, make it suspicious and frightening.","index":4,"dateAdded":1608523724604000,"lastModified":1676860822000000,"id":29,"typeCode":1,"type":"text/x-moz-place","uri":"http://www.shadyurl.com/index.php?e=blank"},{"guid":"cvGsJ0caKN5z","title":"An-Naba' [78:30] - Tanzil Quran Navigator","index":5,"dateAdded":1609045012615000,"lastModified":1676860822000000,"id":30,"typeCode":1,"iconUri":"https://tanzil.net/img/icons/tanzil.svg","type":"text/x-moz-place","uri":"http://tanzil.net/#78:30"},{"guid":"4T31CGWA6ubA","title":"Crohasit - Download PC Games For Free -","index":6,"dateAdded":1656193408210000,"lastModified":1676860822000000,"id":32,"typeCode":1,"type":"text/x-moz-place","uri":"https://crohasit.net/"},{"guid":"BfC5GlHqIS-I","title":"This game can be easy - Wizard101 Forum and Wizard101 Fansite","index":7,"dateAdded":1656296419000000,"lastModified":1676860822000000,"id":33,"typeCode":1,"type":"text/x-moz-place","uri":"http://www.wizard101central.com/forums/showthread.php?505468-This-game-can-be-easy"},{"guid":"KihsVHEo_IWz","title":"EasyPeasy","index":8,"dateAdded":1656360931299000,"lastModified":1676860822000000,"id":34,"typeCode":1,"type":"text/x-moz-place","uri":"https://easypeasymethod.org/"},{"guid":"NH9c5rJgkxeE","title":"youtube audio","index":9,"dateAdded":1659247912125000,"lastModified":1676860822000000,"id":35,"typeCode":1,"type":"text/x-moz-place","uri":"javascript: (function() { if (window[\"_gainNode\"]) { window[\"_gainNode\"].gain.value = parseFloat(prompt('Set the playback rate')); return; } var v = document.querySelector('video'); var audioCtx = new AudioContext(); var source = audioCtx.createMediaElementSource(v); var gainNode = audioCtx.createGain(); gainNode.gain.value = parseFloat(prompt('Set the audio gain')); source.connect(gainNode); gainNode.connect(audioCtx.destination); window[\"_gainNode\"] = gainNode; } )();"},{"guid":"BbwBz7-FRhHF","title":"COP 4538: Data Structures and Algorithms for Information Technology","index":10,"dateAdded":1662488064612000,"lastModified":1676860822000000,"id":36,"typeCode":1,"iconUri":"https://learn.zybooks.com/assets/favicon.ico","type":"text/x-moz-place","uri":"https://learn.zybooks.com/zybook/USFCOP4538YavuzFall2022"},{"guid":"UkQKMFpxPvhV","title":"https://www.youtube.com/watch?v=fL-LL4TyvKI","index":11,"dateAdded":1662528739863000,"lastModified":1676860822000000,"id":37,"typeCode":1,"iconUri":"https://www.youtube.com/s/desktop/52707237/img/favicon_144x144.png","type":"text/x-moz-place","uri":"https://www.youtube.com/watch?v=fL-LL4TyvKI"},{"guid":"582hi1zX8LqW","title":"omega juice","index":12,"dateAdded":1665598392875000,"lastModified":1676860822000000,"id":39,"typeCode":1,"iconUri":"https://www.redditstatic.com/desktop2x/img/favicon/android-icon-192x192.png","type":"text/x-moz-place","uri":"https://www.reddit.com/r/xqcow/comments/xxsrlc/ayo_omega_juicer_went_a_little_off_topic_here/"},{"guid":"2nO49OqlhQpb","title":"CyberLabs","index":13,"dateAdded":1667747733388000,"lastModified":1681933639200000,"id":41,"typeCode":2,"type":"text/x-moz-place-container","children":[{"guid":"uLqZ5EKu5aLl","title":"Attack-Defense Online Lab","index":0,"dateAdded":1667747727457000,"lastModified":1676860822000000,"id":40,"typeCode":1,"iconUri":"https://attackdefense.com/assets/apple-touch-icon.png","type":"text/x-moz-place","uri":"https://attackdefense.com/"},{"guid":"WTgUBSeYZllH","title":"Capture the Flag - Application Security Challenge","index":1,"dateAdded":1667747817988000,"lastModified":1676860822000000,"id":42,"typeCode":1,"iconUri":"https://ctf.komodosec.com/images/favicon.png","type":"text/x-moz-place","uri":"https://ctf.komodosec.com/"},{"guid":"MAk78Our04rc","title":"CryptoHack – A fun, free platform for learning cryptography","index":2,"dateAdded":1667748071770000,"lastModified":1676860822000000,"id":43,"typeCode":1,"iconUri":"https://cryptohack.org/static/favicon/android-icon-192x192.png","type":"text/x-moz-place","uri":"https://cryptohack.org/"},{"guid":"wpseAej8Z9hP","title":"Command Challenge!","index":3,"dateAdded":1667748099720000,"lastModified":1676860822000000,"id":44,"typeCode":1,"type":"text/x-moz-place","uri":"https://cmdchallenge.com/#/print_file_contents"},{"guid":"3nPy55fQtEMy","title":"Exploit Education :: Andrew Griffiths' Exploit Education","index":4,"dateAdded":1667748127563000,"lastModified":1676860822000000,"id":45,"typeCode":1,"iconUri":"https://exploit.education/images/favicon.png","type":"text/x-moz-place","uri":"https://exploit.education/"},{"guid":"spP04RXWxgHJ","title":"Google CTF","index":5,"dateAdded":1667748133067000,"lastModified":1676860822000000,"id":46,"typeCode":1,"iconUri":"https://capturetheflag.withgoogle.com/img/FlagWave.gif","type":"text/x-moz-place","uri":"https://capturetheflag.withgoogle.com/"},{"guid":"KGXZpX2SBp-V","title":"An Interactive Cyber Security Platform | Defend the Web","index":6,"dateAdded":1667748142503000,"lastModified":1676860822000000,"id":47,"typeCode":1,"iconUri":"https://zhr3.co.uk/icons/apple-touch-icon.png","type":"text/x-moz-place","uri":"https://defendtheweb.net/"},{"guid":"pVSwhben8soZ","title":"OverTheWire: Wargames","index":7,"dateAdded":1667748387375000,"lastModified":1676860822000000,"id":49,"typeCode":1,"iconUri":"https://overthewire.org/img/favicon.ico","type":"text/x-moz-place","uri":"https://overthewire.org/wargames/"},{"guid":"7D7z34i2RL_N","title":"PentesterLab: Learn Web Penetration Testing: The Right Way","index":8,"dateAdded":1667748497561000,"lastModified":1676860822000000,"id":50,"typeCode":1,"iconUri":"https://assets.pentesterlab.com/favicon.ico","type":"text/x-moz-place","uri":"https://pentesterlab.com/"},{"guid":"E1a00AaZhPg3","title":"PracticalPentestLabs | Take Your Hacking and Penetration testing Skills to The Next Level.","index":9,"dateAdded":1667748505653000,"lastModified":1676860822000000,"id":51,"typeCode":1,"type":"text/x-moz-place","uri":"https://practicalpentestlabs.com/"},{"guid":"0fJo1yYDX4AY","title":"https://www.amanhardikar.com/mindmaps/Practice.html","index":10,"dateAdded":1667748552455000,"lastModified":1676860822000000,"id":52,"typeCode":1,"charset":"windows-1252","type":"text/x-moz-place","uri":"https://www.amanhardikar.com/mindmaps/Practice.html"},{"guid":"eB3DtumMCNKJ","title":"Penetration test lab \"Test lab\" | Pentestit","index":11,"dateAdded":1667748565938000,"lastModified":1676860822000000,"id":53,"typeCode":1,"iconUri":"https://lab.pentestit.ru/android-chrome-512x512.png","type":"text/x-moz-place","uri":"https://lab.pentestit.ru/"},{"guid":"2DI7ircum5ek","title":"picoCTF - CMU Cybersecurity Competition","index":12,"dateAdded":1667748682786000,"lastModified":1676860822000000,"id":54,"typeCode":1,"iconUri":"https://picoctf.com/apple-touch-icon.png","type":"text/x-moz-place","uri":"https://picoctf.com/"},{"guid":"llLV_0q2dase","title":"Welcome [Root Me : Hacking and Information Security learning platform]","index":13,"dateAdded":1667748740592000,"lastModified":1676860822000000,"id":55,"typeCode":1,"iconUri":"https://www.root-me.org/squelettes/img/rblackGrand16.png?1556531831","type":"text/x-moz-place","uri":"https://www.root-me.org/?lang=en"},{"guid":"EcgdMUJcFhwy","title":"SmashTheStack Wargaming Network","index":14,"dateAdded":1667748820953000,"lastModified":1676860822000000,"id":57,"typeCode":1,"type":"text/x-moz-place","uri":"http://www.smashthestack.org/"},{"guid":"Nt4iGPDuLKFN","title":"The Cryptopals Crypto Challenges","index":15,"dateAdded":1667748856157000,"lastModified":1676860822000000,"id":58,"typeCode":1,"type":"text/x-moz-place","uri":"https://cryptopals.com/"},{"guid":"ziWeLgXNrfvn","title":"TryHackMe | Cyber Security Training","index":16,"dateAdded":1667748866773000,"lastModified":1676860822000000,"id":59,"typeCode":1,"iconUri":"https://assets.tryhackme.com/img/favicon.png","type":"text/x-moz-place","uri":"https://tryhackme.com/"},{"guid":"RyoHHHD0aRGA","title":"Vulnerable By Design ~ VulnHub","index":17,"dateAdded":1667748871249000,"lastModified":1676860822000000,"id":60,"typeCode":1,"iconUri":"https://www.vulnhub.com/static/img/touch-icon-ipad-retina.png","type":"text/x-moz-place","uri":"https://www.vulnhub.com/"},{"guid":"oaNUkaXWACKY","title":"Welcome – W3Challs Hacking Challenges","index":18,"dateAdded":1667748904108000,"lastModified":1676860822000000,"id":61,"typeCode":1,"iconUri":"https://w3challs.com/static/images/favicon.ico","type":"text/x-moz-place","uri":"https://w3challs.com/"},{"guid":"4dB-Ipx05ky8","title":"ZenK-Security :: Communauté de sécurité informatique","index":19,"dateAdded":1667749045313000,"lastModified":1676860822000000,"id":62,"typeCode":1,"iconUri":"https://www.zenk-security.com/assets/img/favicon.ico","type":"text/x-moz-place","uri":"https://www.zenk-security.com/challenges#Steganographie"},{"guid":"r2v6chYCYBb8","title":"CyberDefenders: BlueTeam CTF Challenges","index":20,"dateAdded":1667749048429000,"lastModified":1676860822000000,"id":63,"typeCode":1,"iconUri":"https://cyberdefenders.org/static/img/favicon.ico","type":"text/x-moz-place","uri":"https://cyberdefenders.org/blueteam-ctf-challenges/"},{"guid":"50lC7iv-BuEA","title":"LetsDefend - Blue Team Training Platform","index":21,"dateAdded":1667749093841000,"lastModified":1676860822000000,"id":64,"typeCode":1,"iconUri":"https://letsdefend.io/static/img/favicon.png","type":"text/x-moz-place","uri":"https://letsdefend.io/"},{"guid":"qQ15kigmmNZ2","title":"Hack The Box: Hacking Training For The Best | Individuals & Companies","index":22,"dateAdded":1667749100124000,"lastModified":1676860822000000,"id":65,"typeCode":1,"iconUri":"https://www.hackthebox.com/images/landingv3/favicon.png","type":"text/x-moz-place","uri":"https://www.hackthebox.com/"},{"guid":"8QhIHqGFRT1C","title":"Welcome to pwn.college! | pwn.college","index":23,"dateAdded":1668309564179000,"lastModified":1676860822000000,"id":67,"typeCode":1,"iconUri":"https://pwn.college/assets/images/favicon.png","type":"text/x-moz-place","uri":"https://pwn.college/"},{"guid":"1BQk0XkBqAuM","title":"Nightmare - Nightmare","index":24,"dateAdded":1668400014605000,"lastModified":1676860822000000,"id":68,"typeCode":1,"iconUri":"https://guyinatuxedo.github.io/favicon.svg","type":"text/x-moz-place","uri":"https://guyinatuxedo.github.io/"},{"guid":"Y2UqARWcFMzs","title":"Class Project","index":25,"dateAdded":1668745014689000,"lastModified":1676860822000000,"id":69,"typeCode":1,"iconUri":"https://instructure-uploads.s3.amazonaws.com/account_130000000086643/attachments/50496385/USFLearn%20Nav%20Logo%20mobile%20homescreen%20180%20white.png?AWSAccessKeyId=AKIAJFNFXH2V2O7RPCAA&Expires=1923637177&Signature=SEXRMvzrDwIv%2B6Mu4UGHUUKU14s%3D&response-cache-control=Cache-Control%3Amax-age%3D473364000%2C%20public&response-expires=473364000","type":"text/x-moz-place","uri":"https://usflearn.instructure.com/courses/1714862/assignments/12960019"},{"guid":"OAxEYq_1s7dk","title":"HTB Capture The Flag Platform | Find & Play Hacking CTFs!","index":26,"dateAdded":1668980745458000,"lastModified":1676860822000000,"id":70,"typeCode":1,"iconUri":"https://ctf.hackthebox.com/images/icons/HTB-favicon/apple-touch-icon.png","type":"text/x-moz-place","uri":"https://ctf.hackthebox.com/"},{"guid":"oysilDgC2ARx","title":"Free VMware Workstation Pro 16 to 16.1.1 full license keys with tested (updated with latest verion)","index":27,"dateAdded":1633722869654000,"lastModified":1676860822000000,"id":20,"typeCode":1,"iconUri":"https://github.githubassets.com/favicons/favicon.svg","type":"text/x-moz-place","uri":"https://gist.github.com/williamgh2019/cc2ad94cc18cb930a0aab42ed8d39e6f"},{"guid":"64tHheKNQQGW","title":"Codewars - Achieve mastery through coding practice and developer mentorship","index":28,"dateAdded":1634006069767000,"lastModified":1676860822000000,"id":21,"typeCode":1,"type":"text/x-moz-place","uri":"https://www.codewars.com/"},{"guid":"EoakneOfHI0J","title":"About - Project Euler","index":29,"dateAdded":1634006075250000,"lastModified":1676860822000000,"id":22,"typeCode":1,"type":"text/x-moz-place","uri":"https://projecteuler.net/about"},{"guid":"wVichPId6PqI","title":"LinkedIn Learning: Online Courses for Creative, Technology, Business Skills","index":30,"dateAdded":1644371374803000,"lastModified":1676860822000000,"id":23,"typeCode":1,"type":"text/x-moz-place","uri":"https://www.linkedin.com/learning/"},{"guid":"Zj4cjmKFwSIH","title":"rbndr.us dns rebinding service","index":31,"dateAdded":1669438820067000,"lastModified":1676860822000000,"id":76,"typeCode":1,"charset":"windows-1252","type":"text/x-moz-place","uri":"https://lock.cmpxchg8b.com/rebinder.html"},{"guid":"2Vmx_dAtJM4f","title":"Best Online Cybersecurity Courses & Certifications | HTB Academy","index":32,"dateAdded":1677179179015000,"lastModified":1677179183357000,"id":79,"typeCode":1,"iconUri":"https://academy.hackthebox.com/images/apple-touch-icon.png","type":"text/x-moz-place","uri":"https://academy.hackthebox.com/"},{"guid":"In75cJ9MpsFd","title":"AC-Hunter™ Community Edition - Active Countermeasures","index":33,"dateAdded":1677190166371000,"lastModified":1677190166371000,"id":80,"typeCode":1,"iconUri":"https://www.activecountermeasures.com/wp-content/uploads/2018/08/favicon.png","type":"text/x-moz-place","uri":"https://www.activecountermeasures.com/ac-hunter-community-edition/"},{"guid":"QvGFt9MBzGbR","title":"TryHackMe | A Guide To King of the Hill","index":34,"dateAdded":1677301791089000,"lastModified":1677301791089000,"id":81,"typeCode":1,"iconUri":"https://assets.tryhackme.com/img/favicon.png","type":"text/x-moz-place","uri":"https://tryhackme.com/resources/blog/guide-to-king-of-the-hill"},{"guid":"m2tGyGSKLyh3","title":"randle - Google Search","index":35,"dateAdded":1677986246727000,"lastModified":1677986246727000,"id":82,"typeCode":1,"type":"text/x-moz-place","uri":"https://www.google.com/search?q=randle"},{"guid":"fRuNwFStflfD","title":"Exploit Education :: Andrew Griffiths' Exploit Education","index":36,"dateAdded":1678169894947000,"lastModified":1678169894947000,"id":83,"typeCode":1,"iconUri":"http://exploit.education/images/favicon.png","type":"text/x-moz-place","uri":"http://exploit.education/"},{"guid":"vvrMjSu9zQlo","title":"TCM Security, Inc.","index":37,"dateAdded":1680828044701000,"lastModified":1680828044701000,"id":84,"typeCode":1,"iconUri":"https://process.fs.teachablecdn.com/ADNupMnWyR7kCWRvm76Laz/resize=width:72,height:72/https://file-uploads.teachablecdn.com/40430d7de92349989d27dce71f7756f1/d857671ed3934419bc21e12c8952834e","type":"text/x-moz-place","uri":"https://academy.tcm-sec.com/courses/"},{"guid":"89IBCZhyNRE1","title":"My Dashboard - Zero-Point Security","index":38,"dateAdded":1681918712153000,"lastModified":1681918712153000,"id":85,"typeCode":1,"iconUri":"https://import.cdn.thinkific.com/584845%2Fcustom_site_themes%2Fid%2FgQWDa3dTTJWql9CySzLX_zps_favicon.png","type":"text/x-moz-place","uri":"https://training.zeropointsecurity.co.uk/enrollments"},{"guid":"y6z7QJ2GSbX9","title":"Cyber Ranges","index":39,"dateAdded":1681933639200000,"lastModified":1681933639200000,"id":86,"typeCode":1,"iconUri":"data:image/png;base64,iVBORw0KGgoAAAANSUhEUgAAABAAAAAQCAYAAAAf8/9hAAAACXBIWXMAAAR2AAAEdgG9ParHAAAAAXNSR0IArs4c6QAAAARnQU1BAACxjwv8YQUAAACdSURBVHgB3ZPNCYNQEITnJY+ERPIDIceA5JBzrrmllHSQdBBLsBcLsAU7ULABBVHwnxUUnqA88aA4l4Vl9mNgWAbDLTBCK4zUDAHa4wh1txZ2f9rtuRyAjObr2kDomKDSCWrI56Y0ifq0gBa4rPGnKvDSAl6SQ7eD4YDv/VBNJ0wFAGv/wvO0wZkzOFFWmd+XrQCiFJYfdwOGavoWSre2KH/ZX7/wAAAAAElFTkSuQmCC","type":"text/x-moz-place","uri":"https://dashboard.snaplabs.io/events/p"}]},{"guid":"PaMgE3y1Nqr9","title":"AniMixPlay - Watch HD Anime for Free","index":14,"dateAdded":1667862313347000,"lastModified":1676860822000000,"id":66,"typeCode":1,"iconUri":"https://animixplay.to/icon.png","type":"text/x-moz-place","uri":"https://animixplay.to/"},{"guid":"9Qyc7YipV1Yb","title":"Random","index":15,"dateAdded":1669223362719000,"lastModified":1676860822000000,"id":71,"typeCode":2,"type":"text/x-moz-place-container","children":[{"guid":"23E3A6pEPIe5","title":"HE SAID WHAT?! - Twitch","index":0,"dateAdded":1619652463867000,"lastModified":1676860822000000,"id":14,"typeCode":1,"iconUri":"https://static.twitchcdn.net/assets/favicon-16-52e571ffea063af7a7f4.png","type":"text/x-moz-place","uri":"https://clips.twitch.tv/NiceModernSproutDerp-ARMMv-o5VSCUHg2e"},{"guid":"UB4XCcd6awIo","title":"Streameast","index":1,"dateAdded":1623543020322000,"lastModified":1676860822000000,"id":15,"typeCode":1,"type":"text/x-moz-place","uri":"https://www.streameast.live/home/"},{"guid":"FGjMG5Nijt8Q","title":"Sportsurge","index":2,"dateAdded":1623543190081000,"lastModified":1676860822000000,"id":16,"typeCode":1,"type":"text/x-moz-place","uri":"https://sportsurge.net/#/groups/0"}]},{"guid":"SDaSjjOrkVim","title":"personal","index":16,"dateAdded":1673292797192000,"lastModified":1677179183357000,"id":78,"typeCode":2,"type":"text/x-moz-place-container","children":[{"guid":"vF--rws7KRQO","title":"proton mail","index":0,"dateAdded":1673292775768000,"lastModified":1676860822000000,"id":77,"typeCode":1,"iconUri":"https://mail.proton.me/assets/877c0000356c443ceddf.svg","type":"text/x-moz-place","uri":"https://mail.proton.me/u/1/inbox"}]}]},{"guid":"mobile______","title":"mobile","index":4,"dateAdded":1665084254581000,"lastModified":1665084254640000,"id":6,"typeCode":2,"type":"text/x-moz-place-container","root":"mobileFolder"}]}